odoo/addons/stock_request_separate_picking/README.rst
odoo/addons/stock_request_separate_picking/__init__.py
odoo/addons/stock_request_separate_picking/__manifest__.py
odoo/addons/stock_request_separate_picking/i18n/es.po
odoo/addons/stock_request_separate_picking/i18n/it.po
odoo/addons/stock_request_separate_picking/i18n/stock_request_separate_picking.pot
odoo/addons/stock_request_separate_picking/models/__init__.py
odoo/addons/stock_request_separate_picking/models/res_company.py
odoo/addons/stock_request_separate_picking/models/res_config_settings.py
odoo/addons/stock_request_separate_picking/models/stock_request_abstract.py
odoo/addons/stock_request_separate_picking/models/stock_request_order.py
odoo/addons/stock_request_separate_picking/readme/CONFIGURE.rst
odoo/addons/stock_request_separate_picking/readme/CONTRIBUTORS.rst
odoo/addons/stock_request_separate_picking/readme/DESCRIPTION.rst
odoo/addons/stock_request_separate_picking/readme/HISTORY.rst
odoo/addons/stock_request_separate_picking/static/description/icon.png
odoo/addons/stock_request_separate_picking/static/description/index.html
odoo/addons/stock_request_separate_picking/tests/__init__.py
odoo/addons/stock_request_separate_picking/tests/test_stock_request_separate_picking.py
odoo/addons/stock_request_separate_picking/views/res_config_settings_views.xml
odoo_addon_stock_request_separate_picking-15.0.1.0.0.8.dist-info/METADATA
odoo_addon_stock_request_separate_picking-15.0.1.0.0.8.dist-info/WHEEL
odoo_addon_stock_request_separate_picking-15.0.1.0.0.8.dist-info/top_level.txt
odoo_addon_stock_request_separate_picking-15.0.1.0.0.8.dist-info/RECORD
