Metadata-Version: 2.1
Name: odoo-addon-stock-request-separate-picking
Version: 15.0.1.0.0.8
Summary: Separate one picking per one stock request
Home-page: https://github.com/OCA/stock-logistics-warehouse
Author: Ecosoft, Odoo Community Association (OCA)
Author-email: support@odoo-community.org
License: LGPL-3
Platform: UNKNOWN
Classifier: Programming Language :: Python
Classifier: Framework :: Odoo
Classifier: Framework :: Odoo :: 15.0
Classifier: License :: OSI Approved :: GNU Lesser General Public License v3 (LGPLv3)
Requires-Python: >=3.8
Requires-Dist: odoo-addon-stock-request <15.1dev,>=15.0dev
Requires-Dist: odoo <15.1dev,>=15.0a
